sagellm_comm/__init__.py
sagellm_comm/__init__.pyc
sagellm_comm/backend.pyc
sagellm_comm/gloo_backend.pyc
sagellm_comm/registry.pyc
sagellm_comm/topology.pyc
sagellm_comm/__pycache__/__init__.cpython-311.pyc
sagellm_comm/backends/hccl.pyc
sagellm_comm/backends/nccl.pyc
sagellm_comm/topology/__init__.py
sagellm_comm/topology/__init__.pyc
sagellm_comm/topology/device.pyc
sagellm_comm/topology/link.pyc
isagellm_comm-0.4.0.6.dist-info/METADATA
isagellm_comm-0.4.0.6.dist-info/WHEEL
isagellm_comm-0.4.0.6.dist-info/entry_points.txt
isagellm_comm-0.4.0.6.dist-info/top_level.txt
isagellm_comm-0.4.0.6.dist-info/RECORD
